sqlmodel_filters/__init__.py
sqlmodel_filters/builder.py
sqlmodel_filters/components.py
sqlmodel_filters/exceptions.py
sqlmodel_filters/utils.py
sqlmodel_filters-0.0.12.dist-info/METADATA
sqlmodel_filters-0.0.12.dist-info/WHEEL
sqlmodel_filters-0.0.12.dist-info/licenses/LICENSE
sqlmodel_filters-0.0.12.dist-info/RECORD
