Metadata-Version: 2.4
Name: sqlmodel-filters
Version: 0.0.12
Summary: A Lucene query like filtering for SQLModel
Project-URL: Repository, https://github.com/ninoseki/sqlmodel-filters
Project-URL: Homepage, https://github.com/ninoseki/sqlmodel-filters
Author-email: Manabu Niseki <manabu.niseki@gmail.com>
License-Expression: MIT
License-File: LICENSE
Classifier: License :: OSI Approved :: MIT License
Classifier: Programming Language :: Python
Classifier: Programming Language :: Python :: 3.10
Classifier: Programming Language :: Python :: 3.11
Classifier: Programming Language :: Python :: 3.12
Requires-Python: <4.0,>=3.10
Requires-Dist: luqum~=1.0
Requires-Dist: sqlmodel<1.0,>=0.0.16
